chqr/__init__.py
chqr/constants.py
chqr/creditor.py
chqr/debtor.py
chqr/exceptions.py
chqr/py.typed
chqr/qr_bill.py
chqr/svg_generator.py
chqr/validators.py
chqr-1.2.3.dist-info/WHEEL
chqr-1.2.3.dist-info/METADATA
chqr-1.2.3.dist-info/RECORD
