Metadata-Version: 2.4
Name: chqr
Version: 1.2.3
Summary: Swiss QR bill generation library for Python
Author: Gil Balsiger
Author-email: Gil Balsiger <gil.balsiger@gmail.com>
License-Expression: ISC
Requires-Dist: segno>=1.6.6
Requires-Python: >=3.10
